ic_toolkit_edd/__init__.py
ic_toolkit_edd/abstract/__init__.py
ic_toolkit_edd/abstract/credentials.py
ic_toolkit_edd/abstract/database.py
ic_toolkit_edd/abstract/file_downloader.py
ic_toolkit_edd/abstract/re_execution.py
ic_toolkit_edd/abstract/s3_utils.py
ic_toolkit_edd/abstract/utilities.py
ic_toolkit_edd/beta/__init__.py
ic_toolkit_edd/beta/arquivo/__init__.py
ic_toolkit_edd/beta/arquivo/abstract.py
ic_toolkit_edd/beta/arquivo/original.py
ic_toolkit_edd/beta/arquivo/padronizado.py
ic_toolkit_edd/beta/arquivo/parseado.py
ic_toolkit_edd/beta/arquivo_s3.py
ic_toolkit_edd/beta/etag.py
ic_toolkit_edd/beta/helper.py
ic_toolkit_edd/beta/identify.py
ic_toolkit_edd/beta/input.py
ic_toolkit_edd/beta/input_type.py
ic_toolkit_edd/beta/list_file.py
ic_toolkit_edd/beta/main.py
ic_toolkit_edd/beta/pdf2txt.py
ic_toolkit_edd/beta/re_execution.py
ic_toolkit_edd/beta/sso_manager.py
ic_toolkit_edd/beta/walk.py
ic_toolkit_edd/commands/__init__.py
ic_toolkit_edd/commands/config.py
ic_toolkit_edd/commands/cvtpdf.py
ic_toolkit_edd/commands/gethash.py
ic_toolkit_edd/commands/reexec.py
ic_toolkit_edd/commands/sso.py
ic_toolkit_edd/commands/tiradup.py
ic_toolkit_edd/commands/upload.py
ic_toolkit_edd/commands/walk.py
ic_toolkit_edd/main.py
ic_toolkit_edd-0.3.4.dist-info/entry_points.txt
ic_toolkit_edd-0.3.4.dist-info/METADATA
ic_toolkit_edd-0.3.4.dist-info/WHEEL
ic_toolkit_edd-0.3.4.dist-info/RECORD
