Metadata-Version: 2.1
Name: ic-toolkit-edd
Version: 0.3.4
Summary: 
Author: Marcelo Assis
Author-email: 94455042+marceloapda@users.noreply.github.com
Requires-Python: >=3.7,<4.0
Classifier: Programming Language :: Python :: 3
Classifier: Programming Language :: Python :: 3.7
Classifier: Programming Language :: Python :: 3.8
Classifier: Programming Language :: Python :: 3.9
Classifier: Programming Language :: Python :: 3.10
Classifier: Programming Language :: Python :: 3.11
Requires-Dist: boto3
Requires-Dist: pandas
Requires-Dist: pymysql
Requires-Dist: typer[all] (>=0.4.2,<0.5.0)
